htrdrPy/__init__.py
htrdrPy/data.py
htrdrPy/geometry.py
htrdrPy/helperFunctions.py
htrdrPy/postprocess.py
htrdrPy/script.py
htrdrPy/include/interpolate.py
htrdrPy/include/meshgen.py
htrdrPy/include/meshvisual.py
htrdrPy/include/read.py
htrdrPy/include/write.py
htrdrpy-1.0.2.dist-info/METADATA
htrdrpy-1.0.2.dist-info/WHEEL
htrdrpy-1.0.2.dist-info/licenses/LICENSE
htrdrpy-1.0.2.dist-info/RECORD
