Metadata-Version: 2.4
Name: htrdrPy
Version: 1.0.2
Summary: htrdrPy is a library that aims to wrap the radiative transfer code htrdr-planets, aiming to make the use of htrdr-planets more user-friendly.
Project-URL: Homepage, https://gitlab.obspm.fr/aarfaux/htrdr-wrapper.git
Project-URL: Documentation, https://htrdr-wrapper-ebbb17.pages.obspm.fr
Author-email: Anthony Arfaux <anthony.arfaux@obspm.fr>
License-Expression: GPL-3.0-only
License-File: LICENSE
Classifier: Operating System :: OS Independent
Classifier: Programming Language :: Python :: 3
Requires-Python: >=3.9
